{
    "css": {
        "functions": {},
        "variables": {},
        "classes": {}
    },
    "js": {
        "functions": {},
        "variables": {},
        "classes": {}
    },
    "php": {
        "functions": {
            "stripslashes_gpc": "(&$value)",
            "image": "($file, $w, $h, $attribs=true, $crop=false)",
            "age": "($dob)",
            "alert": "($error)",
            "analytics": "($id)",
            "calc_grids": "($pcodeA)",
            "check_table": "($table,$fields)",
            "clean": "($string)",
            "current_tab": "( $tab, $index=0)",
            "datediff": "($endDate, $beginDate)",
            "dateformat": "( $format, $date, $uk=true)",
            "debug": "($var,$die)",
            "shutdown": "()",
            "email_template": "($email,$subject,$reps,$headers,$language='en')",
            "starts_with": "($haystack, $needle)",
            "ends_with": "($haystack, $needle)",
            "error": "($error)",
            "error_handler": "($errno, $errstr, $errfile, $errline, $errcontext='')",
            "escape": "($string)",
            "escape_strip": "($string)",
            "escape_clean": "($string)",
            "file_ext": "($file)",
            "file_size": "($size)",
            "form_to_db": "($type)",
            "format_mobile": "($mobile)",
            "format_postcode": "($postcode)",
            "generate_password": "()",
            "get_client_language": "($availableLanguages, $default='en')",
            "get_options": "($table,$field,$where=false)",
            "html": "($string)",
            "html_options": "()",
            "html_options_optoutput": "($key, $value, $selected, $disabled)",
            "html_options_optgroup": "($key, $values, $selected)",
            "html_to_absolute": "($txt, $base_url)",
            "is_alphanumeric": "($string)",
            "is_animated": "($filename)",
            "is_assoc_array": "($var)",
            "is_domain": "($domain)",
            "is_email": "($email)",
            "is_nino": "($code)",
            "is_odd": "($number)",
            "is_postcode": "($code)",
            "is_url": "($str)",
            "load_js": "($libs)",
            "make_timestamp": "($string)",
            "mysql2csv": "($query,$filename='data')",
            "num2alpha": "($n)",
            "options": "($options,$selected='')",
            "parse_links": "($text)",
            "redirect": "($url,$_301=false)",
            "sec2hms": "($sec, $padHours = false)",
            "spaced": "($str)",
            "sql_query": "($query,$single=false)",
            "table_exists": "($table)",
            "thumb": "($file,$max_width=200,$max_height=200,$default=NULL,$save=NULL,$output=true)",
            "truncate": "($string, $max = 50, $rep = '..')",
            "underscored": "($str)",
            "url_grab_title": "($url)",
            "validate": "($fields, $required, $array=true)",
            "youtube_id_from_url": "($url)"
        },
        "variables": {
            "$cms": {
                "type": "class",
                "value": "cms"
            }
        },
        "classes": {
            "cms": {
                "functions": {
                    "cms": "()",
                    "file_fields": 1,
                    "cms_multiple_select_fields": 1,
                    "cms_privileges_fields": 1,
                    "db_field_name": 1,
                    "delete_items": "($section,$items)",
                    "delete_all_pages": "($section,$conditions)",
                    "get": "($sections,$conditions=NULL,$num_results=NULL,$order=NULL,$asc=true,$prefix=NULL,$return_query=false)",
                    "delete": "($section,$ids)",
                    "trigger_event": "($event, $args)",
                    "language": 1,
                    "section": 1,
                    "p": 1,
                    "rows": 1,
                    "inline": 1,
                    "set_section": "($section,$id,$editable_fields)",
                    "table": 1,
                    "editable_fields": 1,
                    "field_id": 1,
                    "id": 1,
                    "content": 1,
                    "set_language": "( $language)",
                    "get_label": "()",
                    "get_children": 1,
                    "get_field": "($name,$attribs='',$separator='',$placeholder='')",
                    "get_options": "($name)",
                    "get_value": "($name,$return=true)",
                    "admin": "()",
                    "template": 1,
                    "default_section": "($option)",
                    "validate": "($data)",
                    "build_query": 1,
                    "query": 1,
                    "save": "($data)",
                    "choose_filter": "()",
                    "configure": "()",
                    "dropdowns": "()",
                    "orders": "()",
                    "order": "()",
                    "login": "()",
                    "main": "()",
                    "email_templates": "()",
                    "preferences": "()",
                    "logout": "()"
                }
            }
        }
    },
    "html": {
        "functions": {
            "": "()"
        },
        "variables": {},
        "classes": {}
    }
}